rnaseqflow/__init__.py
rnaseqflow/__main__.py
rnaseqflow/cliutils.py
rnaseqflow/workflow.py
rnaseqflow-0.2.2.dist-info/DESCRIPTION.rst
rnaseqflow-0.2.2.dist-info/METADATA
rnaseqflow-0.2.2.dist-info/RECORD
rnaseqflow-0.2.2.dist-info/WHEEL
rnaseqflow-0.2.2.dist-info/entry_points.txt
rnaseqflow-0.2.2.dist-info/metadata.json
rnaseqflow-0.2.2.dist-info/top_level.txt
