Metadata-Version: 2.0
Name: rnaseqflow
Version: 0.2.2
Summary: RNASeq Preprocessor
Home-page: https://github.com/jpalpant/rnaseqflow
Author: Justin Palpant
Author-email: justin@palpant.us
License: GPLv3
Platform: UNKNOWN
